budy/__init__.py
budy/main.py
budy/controllers/__init__.py
budy/controllers/api/__init__.py
budy/controllers/api/account.py
budy/controllers/api/address.py
budy/controllers/api/bag.py
budy/controllers/api/base.py
budy/controllers/api/brand.py
budy/controllers/api/category.py
budy/controllers/api/collection.py
budy/controllers/api/color.py
budy/controllers/api/country.py
budy/controllers/api/currency.py
budy/controllers/api/easypay.py
budy/controllers/api/easypay_v2.py
budy/controllers/api/media.py
budy/controllers/api/order.py
budy/controllers/api/product.py
budy/controllers/api/referral.py
budy/controllers/api/root.py
budy/controllers/api/season.py
budy/controllers/api/section.py
budy/controllers/api/seeplus.py
budy/controllers/api/store.py
budy/controllers/api/subscription.py
budy/controllers/api/voucher.py
budy/controllers/web/__init__.py
budy/controllers/web/_stripe.py
budy/controllers/web/admin.py
budy/controllers/web/base.py
budy/controllers/web/order.py
budy/models/__init__.py
budy/models/account.py
budy/models/address.py
budy/models/bag.py
budy/models/bag_line.py
budy/models/base.py
budy/models/brand.py
budy/models/bundle.py
budy/models/bundle_line.py
budy/models/category.py
budy/models/collection.py
budy/models/color.py
budy/models/composition.py
budy/models/country.py
budy/models/currency.py
budy/models/exchange_rate.py
budy/models/group.py
budy/models/live_model.py
budy/models/measurement.py
budy/models/media.py
budy/models/order.py
budy/models/order_line.py
budy/models/product.py
budy/models/referral.py
budy/models/season.py
budy/models/section.py
budy/models/store.py
budy/models/subscription.py
budy/models/voucher.py
budy/models/voucher_usage.py
budy/models/wishlist.py
budy/models/wishlist_line.py
budy/static/js/main.js
budy/templates/signin.html.tpl
budy/templates/order/me.html.tpl
budy/templates/partials/base.html.tpl
budy/templates/partials/external.html.tpl
budy/templates/partials/internal.html.tpl
budy/test/__init__.py
budy/test/account.py
budy-0.8.29.dist-info/METADATA
budy-0.8.29.dist-info/WHEEL
budy-0.8.29.dist-info/top_level.txt
budy-0.8.29.dist-info/RECORD
